{
  "project_info": {
    "project_number": "205818698086",
    "project_id": "ontime-bec6e",
    "storage_bucket": "ontime-bec6e.firebasestorage.app"
  },
  "client": [
    {
      "client_info": {
        "mobilesdk_app_id": "1:205818698086:android:b47d2f9d5d77d5379f90a7",
        "android_client_info": {
          "package_name": "com.example.checkin"
        }
      },
      "oauth_client": [],
      "api_key": [
        {
          "current_key": "AIzaSyBl2TzNTMYj3lQQlw1mo58fESulUW9OYGc"
        }
      ],
      "services": {
        "appinvite_service": {
          "other_platform_oauth_client": []
        }
      }
    }
  ],
  "configuration_version": "1"
}